config/config.v
`define WORD_LEN 32
`define EXE_CMD_LEN 4
`define RA_LEN 4
`define RAM_DEPTH 64
`define MEMORY_ADDR_LEN 7
`define SIGN_EXTEND_LEN 16
`define PC_LEN 32
`define SHIFT_LEN 8

Modules/ShiftRegister/shiftRegister.v
`include "../../config/config.v"

module shiftreg # (parameter N = `SHIFT_LEN) // Corrige para usar `SHIFT_LEN` como valor padrão para N
   (input clk,
    input reset, load,
    input sin,
    input [N-1:0] data_in,
    output reg [N-1:0] data_out,
    output sout);

    always @(posedge clk or posedge reset)
        if (reset)
            data_out <= 0;
        else if (load)
            data_out <= data_in;
        else
            data_out <= {data_out[N-2:0], sin}; // Desloca e insere `sin` na posição menos significativa

    assign sout = data_out[N-1]; // Corrigido para usar `N-1` para o bit mais significativo

endmodule

Modules/ShiftRegister/shiftRegister_tb.v
`timescale 1ns / 1ps

module shiftreg_tb;

    // Parâmetros do Testbench
    parameter N = `SHIFT_LEN; 
    parameter CLK_PERIOD = 10; // Período do clock em ns

    // Entradas
    reg clk;
    reg reset;
    reg load;
    reg sin;
    reg [N-1:0] data_in;

    // Saídas
    wire [N-1:0] data_out;
    wire sout;

    // Variáveis do Testbench
    reg [N-1:0] expected_data_out; // Declarada aqui para uso no bloco initial

    // Instância do módulo a ser testado
    shiftreg #(.N(N)) uut (
        .clk(clk),
        .reset(reset),
        .load(load),
        .sin(sin),
        .data_in(data_in),
        .data_out(data_out),
        .sout(sout)
    );

    // Geração de clock
    always #(CLK_PERIOD/2) clk = ~clk;

    // Procedimento inicial
    initial begin
        // Inicialização
        clk = 0;
        reset = 1;
        load = 0;
        sin = 0;
        data_in = 0;
               $dumpfile("shiftreg_tb.vcd");
        $dumpvars(0, shiftreg_tb);
        // Reset do sistema
        #20;
        reset = 0;

        // Teste de carga de dados
        #10;
        load = 1;
        data_in = 8'b10101010; // Exemplo de padrão de dados
        #10;
        load = 0;

        // print data_out
        $display("data_out = %b", data_out);

        // Teste de deslocamento com sin = 1
        #20;
        sin = 1;
        #10;
        sin = 0;
        // print data_out
        $display("data_out = %b", data_out);

        // Mais ciclos de clock para observação
        #100;

        // Preparação do valor esperado
        expected_data_out = {data_in[N-2:0], 1'b1}; // Prepara o valor esperado antes da verificação



        // Finaliza a simulação
        $finish;
    end

endmodule

Modules/ShiftRegister/shiftreg_tb.vcd
$date
	Tue Feb 20 00:08:05 2024
$end
$version
	Icarus Verilog
$end
$timescale
	1ps
$end
$scope module shiftreg_tb $end
$var wire 1 ! sout $end
$var wire 8 " data_out [7:0] $end
$var reg 1 # clk $end
$var reg 8 $ data_in [7:0] $end
$var reg 8 % expected_data_out [7:0] $end
$var reg 1 & load $end
$var reg 1 ' reset $end
$var reg 1 ( sin $end
$scope module uut $end
$var wire 1 # clk $end
$var wire 8 ) data_in [7:0] $end
$var wire 1 & load $end
$var wire 1 ' reset $end
$var wire 1 ( sin $end
$var wire 1 ! sout $end
$var reg 8 * data_out [7:0] $end
$upscope $end
$upscope $end
$enddefinitions $end
#0
$dumpvars
b0 *
b0 )
0(
1'
0&
bx %
b0 $
0#
b0 "
0!
$end
#5000
1#
#10000
0#
#15000
1#
#20000
0#
0'
#25000
1#
#30000
0#
b10101010 $
b10101010 )
1&
#35000
1!
b10101010 "
b10101010 *
1#
#40000
0#
0&
#45000
0!
b1010100 "
b1010100 *
1#
#50000
0#
#55000
1!
b10101000 "
b10101000 *
1#
#60000
0#
1(
#65000
0!
b1010001 "
b1010001 *
1#
#70000
0#
0(
#75000
1!
b10100010 "
b10100010 *
1#
#80000
0#
#85000
0!
b1000100 "
b1000100 *
1#
#90000
0#
#95000
1!
b10001000 "
b10001000 *
1#
#100000
0#
#105000
0!
b10000 "
b10000 *
1#
#110000
0#
#115000
b100000 "
b100000 *
1#
#120000
0#
#125000
b1000000 "
b1000000 *
1#
#130000
0#
#135000
1!
b10000000 "
b10000000 *
1#
#140000
0#
#145000
0!
b0 "
b0 *
1#
#150000
0#
#155000
1#
#160000
0#
#165000
1#
#170000
0#
b1010101 %
