config/config.v
`define WORD_LEN 32
`define EXE_CMD_LEN 4
`define RA_LEN 4
`define RAM_DEPTH 64
`define MEMORY_ADDR_LEN 7
`define SIGN_EXTEND_LEN 16
`define PC_LEN 32
`define SHIFT_LEN 8

Modules/ProgamingCounting/pcModule.v
`include "../../config/config.v"

module ProgramCounter(
    input clk,            // Clock signal
    input reset,          // Asynchronous reset signal
    input enable,         // Enable signal to increment or load the PC
    input [`WORD_LEN-1:0] newPC,   // Input for loading a new PC value
    output reg [`WORD_LEN-1:0] PC  // Current PC value
);

// On every positive edge of the clock or an active-high reset signal
always @(posedge clk or posedge reset) begin
    if (reset) begin
        // Asynchronously reset the PC to 0
        PC <= `WORD_LEN'b0;
    end else if (enable) begin
        // If enabled, increment the PC by 4 (assuming 4-byte instruction width)
        // Alternatively, load a new value into the PC
        PC <= newPC;
    end
end

endmodule

Modules/ProgamingCounting/pcModule_tb.v
`include "../../config/config.v"
`timescale 1ns / 1ps

module ProgramCounter_tb;

// Inputs
reg clk;
reg reset;
reg enable;
reg [`WORD_LEN-1:0] newPC;

// Output
wire [`WORD_LEN-1:0] PC;

// Instantiate the Unit Under Test (UUT)
ProgramCounter uut (
    .clk(clk),
    .reset(reset),
    .enable(enable),
    .newPC(newPC),
    .PC(PC)
);

// Clock generation
initial begin
    clk = 0;
    forever #10 clk = ~clk; // Toggle clock every 10 ns
end

// Test cases
initial begin
    // Initialize Inputs
    reset = 1;
    enable = 0;
    newPC = 0;

    $dumpfile("ProgramCounter_tb.vcd");
    $dumpvars(0, ProgramCounter_tb);

    // Wait 100 ns for global reset to finish
    #100;
    
    // Deassert reset
    reset = 0; 
    enable = 1;
    newPC = 32'h0000_0004; // Assuming an increment by 4 (typical for 32-bit instructions)
    
    // Wait for a couple of clock cycles
    #20;
    
    // Load a new value into PC
    newPC = 32'h0000_00A0;
    
    // Wait for a couple of clock cycles
    #20;
    
    // Disable PC increment/loading
    enable = 0;

    // Wait for a couple of clock cycles to observe no change in PC
    #20;
    
    // Enable again with a different newPC
    enable = 1;
    newPC = 32'h0000_0100;

    // Wait and observe
    #20;
    
    // Assert reset to see if PC goes to 0
    reset = 1;
    #10;
    reset = 0; // Deassert reset
    
    // Finish simulation
    #10;
    $finish;
end

endmodule

Modules/ProgamingCounting/ProgramCounter_tb.vcd
$date
	Mon Feb 19 22:47:22 2024
$end
$version
	Icarus Verilog
$end
$timescale
	1ps
$end
$scope module ProgramCounter_tb $end
$var wire 32 ! PC [31:0] $end
$var reg 1 " clk $end
$var reg 1 # enable $end
$var reg 32 $ newPC [31:0] $end
$var reg 1 % reset $end
$scope module uut $end
$var wire 1 " clk $end
$var wire 1 # enable $end
$var wire 32 & newPC [31:0] $end
$var wire 1 % reset $end
$var reg 32 ' PC [31:0] $end
$upscope $end
$upscope $end
$enddefinitions $end
#0
$dumpvars
b0 '
b0 &
1%
b0 $
0#
0"
b0 !
$end
#10000
1"
#20000
0"
#30000
1"
#40000
0"
#50000
1"
#60000
0"
#70000
1"
#80000
0"
#90000
1"
#100000
0"
b100 $
b100 &
1#
0%
#110000
b100 !
b100 '
1"
#120000
0"
b10100000 $
b10100000 &
#130000
b10100000 !
b10100000 '
1"
#140000
0"
0#
#150000
1"
#160000
0"
b100000000 $
b100000000 &
1#
#170000
b100000000 !
b100000000 '
1"
#180000
b0 !
b0 '
0"
1%
#190000
b100000000 !
b100000000 '
1"
0%
